cyberfusion/FermSupport/__init__.py
cyberfusion/FermSupport/configuration/__init__.py
cyberfusion/FermSupport/configuration/custom_lines.py
cyberfusion/FermSupport/configuration/variables.py
cyberfusion/FermSupport/exceptions/__init__.py
python3_cyberfusion_ferm_support-1.3.dist-info/METADATA
python3_cyberfusion_ferm_support-1.3.dist-info/WHEEL
python3_cyberfusion_ferm_support-1.3.dist-info/top_level.txt
python3_cyberfusion_ferm_support-1.3.dist-info/RECORD
