Metadata-Version: 2.4
Name: python3-cyberfusion-ferm-support
Version: 1.3
Summary: Library for ferm.
Author-email: Cyberfusion <support@cyberfusion.io>
Project-URL: Source, https://github.com/CyberfusionIO/python3-cyberfusion-ferm-support
Requires-Dist: python3-cyberfusion-common~=2.12
Requires-Dist: python3-cyberfusion-systemd-support~=2.3.1
